{
  "typeName": "AWS::RDS::DBSecurityGroupIngress",
  "description": "Resource Type definition for AWS::RDS::DBSecurityGroupIngress",
  "additionalProperties": false,
  "properties": {
    "Id": {
      "type": "string",
      "markdownDescription": "\n\n---\n\nRequired: No\n\nType: string     \n\nUpdate requires: No interruption "
    },
    "CIDRIP": {
      "type": "string",
      "markdownDescription": "\n\n---\n\nRequired: No\n\nType: string     \n\nUpdate requires: No interruption "
    },
    "DBSecurityGroupName": {
      "type": "string",
      "markdownDescription": "\n\n---\n\nRequired: No\n\nType: string     \n\nUpdate requires: No interruption "
    },
    "EC2SecurityGroupId": {
      "type": "string",
      "markdownDescription": "\n\n---\n\nRequired: No\n\nType: string     \n\nUpdate requires: No interruption "
    },
    "EC2SecurityGroupName": {
      "type": "string",
      "markdownDescription": "\n\n---\n\nRequired: No\n\nType: string     \n\nUpdate requires: No interruption "
    },
    "EC2SecurityGroupOwnerId": {
      "type": "string",
      "markdownDescription": "\n\n---\n\nRequired: No\n\nType: string     \n\nUpdate requires: No interruption "
    }
  },
  "required": [
    "DBSecurityGroupName"
  ],
  "primaryIdentifier": [
    "/properties/Id"
  ],
  "readOnlyProperties": [
    "/properties/Id"
  ]
}