{
  "typeName": "AWS::EMR::InstanceGroupConfig",
  "description": "Resource Type definition for AWS::EMR::InstanceGroupConfig",
  "additionalProperties": false,
  "properties": {
    "JobFlowId": {
      "type": "string",
      "markdownDescription": "\n\n---\n\nRequired: No\n\nType: string     \n\nUpdate requires: No interruption "
    },
    "AutoScalingPolicy": {
      "$ref": "#/definitions/AutoScalingPolicy",
      "markdownDescription": "\n\n---\n\nRequired: No\n\nType:      \n\nUpdate requires: No interruption "
    },
    "BidPrice": {
      "type": "string",
      "markdownDescription": "\n\n---\n\nRequired: No\n\nType: string     \n\nUpdate requires: No interruption "
    },
    "InstanceCount": {
      "type": "integer",
      "markdownDescription": "\n\n---\n\nRequired: No\n\nType: integer     \n\nUpdate requires: No interruption "
    },
    "EbsConfiguration": {
      "$ref": "#/definitions/EbsConfiguration",
      "markdownDescription": "\n\n---\n\nRequired: No\n\nType:      \n\nUpdate requires: No interruption "
    },
    "InstanceRole": {
      "type": "string",
      "markdownDescription": "\n\n---\n\nRequired: No\n\nType: string     \n\nUpdate requires: No interruption "
    },
    "CustomAmiId": {
      "type": "string",
      "markdownDescription": "\n\n---\n\nRequired: No\n\nType: string     \n\nUpdate requires: No interruption "
    },
    "Id": {
      "type": "string",
      "markdownDescription": "\n\n---\n\nRequired: No\n\nType: string     \n\nUpdate requires: No interruption "
    },
    "Configurations": {
      "type": "array",
      "uniqueItems": true,
      "items": {
        "$ref": "#/definitions/Configuration"
      },
      "markdownDescription": "\n\n---\n\nRequired: No\n\nType: array     \n\nUpdate requires: No interruption "
    },
    "InstanceType": {
      "type": "string",
      "markdownDescription": "\n\n---\n\nRequired: No\n\nType: string     \n\nUpdate requires: No interruption "
    },
    "Market": {
      "type": "string",
      "markdownDescription": "\n\n---\n\nRequired: No\n\nType: string     \n\nUpdate requires: No interruption "
    },
    "Name": {
      "type": "string",
      "markdownDescription": "\n\n---\n\nRequired: No\n\nType: string     \n\nUpdate requires: No interruption "
    }
  },
  "definitions": {
    "AutoScalingPolicy": {
      "type": "object",
      "additionalProperties": false,
      "properties": {
        "Rules": {
          "type": "array",
          "uniqueItems": true,
          "items": {
            "$ref": "#/definitions/ScalingRule"
          }
        },
        "Constraints": {
          "$ref": "#/definitions/ScalingConstraints"
        }
      },
      "required": [
        "Constraints",
        "Rules"
      ]
    },
    "VolumeSpecification": {
      "type": "object",
      "additionalProperties": false,
      "properties": {
        "SizeInGB": {
          "type": "integer"
        },
        "VolumeType": {
          "type": "string"
        },
        "Iops": {
          "type": "integer"
        }
      },
      "required": [
        "SizeInGB",
        "VolumeType"
      ]
    },
    "CloudWatchAlarmDefinition": {
      "type": "object",
      "additionalProperties": false,
      "properties": {
        "MetricName": {
          "type": "string"
        },
        "ComparisonOperator": {
          "type": "string"
        },
        "Statistic": {
          "type": "string"
        },
        "Dimensions": {
          "type": "array",
          "uniqueItems": true,
          "items": {
            "$ref": "#/definitions/MetricDimension"
          }
        },
        "Period": {
          "type": "integer"
        },
        "EvaluationPeriods": {
          "type": "integer"
        },
        "Unit": {
          "type": "string"
        },
        "Namespace": {
          "type": "string"
        },
        "Threshold": {
          "type": "number"
        }
      },
      "required": [
        "MetricName",
        "ComparisonOperator",
        "Period",
        "Threshold"
      ]
    },
    "EbsConfiguration": {
      "type": "object",
      "additionalProperties": false,
      "properties": {
        "EbsBlockDeviceConfigs": {
          "type": "array",
          "uniqueItems": true,
          "items": {
            "$ref": "#/definitions/EbsBlockDeviceConfig"
          }
        },
        "EbsOptimized": {
          "type": "boolean"
        }
      }
    },
    "Configuration": {
      "type": "object",
      "additionalProperties": false,
      "properties": {
        "ConfigurationProperties": {
          "type": "object",
          "patternProperties": {
            "[a-zA-Z0-9]+": {
              "type": "string"
            }
          }
        },
        "Configurations": {
          "type": "array",
          "uniqueItems": true,
          "items": {
            "$ref": "#/definitions/Configuration"
          }
        },
        "Classification": {
          "type": "string"
        }
      }
    },
    "ScalingAction": {
      "type": "object",
      "additionalProperties": false,
      "properties": {
        "Market": {
          "type": "string"
        },
        "SimpleScalingPolicyConfiguration": {
          "$ref": "#/definitions/SimpleScalingPolicyConfiguration"
        }
      },
      "required": [
        "SimpleScalingPolicyConfiguration"
      ]
    },
    "SimpleScalingPolicyConfiguration": {
      "type": "object",
      "additionalProperties": false,
      "properties": {
        "ScalingAdjustment": {
          "type": "integer"
        },
        "CoolDown": {
          "type": "integer"
        },
        "AdjustmentType": {
          "type": "string"
        }
      },
      "required": [
        "ScalingAdjustment"
      ]
    },
    "ScalingConstraints": {
      "type": "object",
      "additionalProperties": false,
      "properties": {
        "MinCapacity": {
          "type": "integer"
        },
        "MaxCapacity": {
          "type": "integer"
        }
      },
      "required": [
        "MinCapacity",
        "MaxCapacity"
      ]
    },
    "EbsBlockDeviceConfig": {
      "type": "object",
      "additionalProperties": false,
      "properties": {
        "VolumeSpecification": {
          "$ref": "#/definitions/VolumeSpecification"
        },
        "VolumesPerInstance": {
          "type": "integer"
        }
      },
      "required": [
        "VolumeSpecification"
      ]
    },
    "ScalingTrigger": {
      "type": "object",
      "additionalProperties": false,
      "properties": {
        "CloudWatchAlarmDefinition": {
          "$ref": "#/definitions/CloudWatchAlarmDefinition"
        }
      },
      "required": [
        "CloudWatchAlarmDefinition"
      ]
    },
    "ScalingRule": {
      "type": "object",
      "additionalProperties": false,
      "properties": {
        "Action": {
          "$ref": "#/definitions/ScalingAction"
        },
        "Description": {
          "type": "string"
        },
        "Trigger": {
          "$ref": "#/definitions/ScalingTrigger"
        },
        "Name": {
          "type": "string"
        }
      },
      "required": [
        "Action",
        "Trigger",
        "Name"
      ]
    },
    "MetricDimension": {
      "type": "object",
      "additionalProperties": false,
      "properties": {
        "Value": {
          "type": "string"
        },
        "Key": {
          "type": "string"
        }
      },
      "required": [
        "Value",
        "Key"
      ]
    }
  },
  "required": [
    "JobFlowId",
    "InstanceCount",
    "InstanceRole",
    "InstanceType"
  ],
  "createOnlyProperties": [
    "/properties/InstanceRole",
    "/properties/JobFlowId",
    "/properties/Name",
    "/properties/InstanceType",
    "/properties/CustomAmiId",
    "/properties/Configurations",
    "/properties/EbsConfiguration",
    "/properties/Market",
    "/properties/BidPrice"
  ],
  "primaryIdentifier": [
    "/properties/Id"
  ],
  "readOnlyProperties": [
    "/properties/Id"
  ]
}