{
  "typeName": "AWS::SecretsManager::SecretTargetAttachment",
  "description": "Resource Type definition for AWS::SecretsManager::SecretTargetAttachment",
  "additionalProperties": false,
  "properties": {
    "Id": {
      "type": "string",
      "markdownDescription": "\n\n---\n\nRequired: No\n\nType: string     \n\nUpdate requires: No interruption "
    },
    "SecretId": {
      "type": "string",
      "markdownDescription": "\n\n---\n\nRequired: No\n\nType: string     \n\nUpdate requires: No interruption "
    },
    "TargetType": {
      "type": "string",
      "markdownDescription": "\n\n---\n\nRequired: No\n\nType: string     \n\nUpdate requires: No interruption "
    },
    "TargetId": {
      "type": "string",
      "markdownDescription": "\n\n---\n\nRequired: No\n\nType: string     \n\nUpdate requires: No interruption "
    }
  },
  "required": [
    "TargetType",
    "TargetId",
    "SecretId"
  ],
  "primaryIdentifier": [
    "/properties/Id"
  ],
  "readOnlyProperties": [
    "/properties/Id"
  ]
}