{
  "$schema": "http://json-schema.org/draft-07/schema#",
  "$id": "https://aws.amazon.com/cloudformation/resources/AWS_SageMaker_ModelPackageGroup.json",
  "title": "",
  "description": "CFN JSON specification generated from version 68.1.0",
  "type": "object",
  "definitions": {
    "AWS_SageMaker_ModelPackageGroup": {
      "type": "object",
      "description": "http://docs.aws.amazon.com/AWSCloudFormation/latest/UserGuide/aws-properties-sagemaker-modelpackagegroup.html",
      "allOf": [
        {
          "type": "object",
          "properties": {
            "Type": {
              "description": "http://docs.aws.amazon.com/AWSCloudFormation/latest/UserGuide/aws-properties-sagemaker-modelpackagegroup.html",
              "type": "string",
              "enum": ["AWS::SageMaker::ModelPackageGroup"]
            },
            "Properties": {
              "$ref": "properties/aws-sagemaker-modelpackagegroup.json"
            }
          },
          "required": ["Type"]
        },
        {
          "$ref": "attributes.schema.json#/definitions/ResourceAttributes"
        }
      ],

      "additionalProperties": false
    }
  }
}