{
  "typeName": "AWS::AppSync::GraphQLSchema",
  "description": "Resource Type definition for AWS::AppSync::GraphQLSchema",
  "additionalProperties": false,
  "properties": {
    "Id": {
      "type": "string",
      "markdownDescription": "\n\n---\n\nRequired: No\n\nType: string     \n\nUpdate requires: No interruption "
    },
    "Definition": {
      "type": "string",
      "markdownDescription": "\n\n---\n\nRequired: No\n\nType: string     \n\nUpdate requires: No interruption "
    },
    "DefinitionS3Location": {
      "type": "string",
      "markdownDescription": "\n\n---\n\nRequired: No\n\nType: string     \n\nUpdate requires: No interruption "
    },
    "ApiId": {
      "type": "string",
      "markdownDescription": "\n\n---\n\nRequired: No\n\nType: string     \n\nUpdate requires: No interruption "
    }
  },
  "required": [
    "ApiId"
  ],
  "createOnlyProperties": [
    "/properties/ApiId"
  ],
  "primaryIdentifier": [
    "/properties/Id"
  ],
  "readOnlyProperties": [
    "/properties/Id"
  ]
}