{
  "typeName": "AWS::SES::Template",
  "description": "Resource Type definition for AWS::SES::Template",
  "sourceUrl": "https://github.com/aws-cloudformation/aws-cloudformation-resource-providers-ses.git",
  "definitions": {
    "Template": {
      "type": "object",
      "additionalProperties": false,
      "description": "The content of the email, composed of a subject line, an HTML part, and a text-only part",
      "properties": {
        "TemplateName": {
          "description": "The name of the template.",
          "type": "string",
          "maxLength": 64,
          "minLength": 1,
          "markdownDescription": "The name of the template.\n\n---\n\nRequired: No  \nType: String  \nMinimum Length: 1  \nMaximum Length: 64  \nPattern: ^[a-zA-Z0-9_-]{1,64}$  \nUpdate requires: No interruption"
        },
        "SubjectPart": {
          "description": "The subject line of the email.",
          "type": "string",
          "markdownDescription": "The subject line of the email.\n\n---\n\nRequired: Yes  \nType: String  \nUpdate requires: No interruption"
        },
        "TextPart": {
          "description": "The email body that is visible to recipients whose email clients do not display HTML content.",
          "type": "string",
          "markdownDescription": "The email body that is visible to recipients whose email clients do not display HTML content.\n\n---\n\nRequired: No  \nType: String  \nUpdate requires: No interruption"
        },
        "HtmlPart": {
          "description": "The HTML body of the email.",
          "type": "string",
          "markdownDescription": "The HTML body of the email.\n\n---\n\nRequired: No  \nType: String  \nUpdate requires: No interruption"
        }
      },
      "required": [
        "SubjectPart"
      ],
      "markdownDescription": "The content of the email, composed of a subject line, an HTML part, and a text-only part\n\n---\n\nRequired: No  \nUpdate requires: Replacement"
    }
  },
  "properties": {
    "Template": {
      "$ref": "#/definitions/Template"
    }
  },
  "additionalProperties": false,
  "readOnlyProperties": [
    "/properties/Id"
  ],
  "primaryIdentifier": [
    "/properties/Id"
  ],
  "createOnlyProperties": [
    "/properties/Template/TemplateName"
  ],
  "handlers": {
    "create": {
      "permissions": [
        "ses:CreateEmailTemplate",
        "ses:GetEmailTemplate",
        "ses:CreateTemplate",
        "ses:GetTemplate"
      ]
    },
    "read": {
      "permissions": [
        "ses:GetEmailTemplate",
        "ses:GetTemplate"
      ]
    },
    "delete": {
      "permissions": [
        "ses:DeleteEmailTemplate",
        "ses:DeleteTemplate"
      ]
    },
    "update": {
      "permissions": [
        "ses:GetEmailTemplate",
        "ses:UpdateEmailTemplate",
        "ses:GetTemplate",
        "ses:UpdateTemplate"
      ]
    },
    "list": {
      "permissions": [
        "ses:ListEmailTemplates",
        "ses:ListTemplates"
      ]
    }
  },
  "attributes": {
    "Id": {
      "type": "string",
      "markdownDescription": "\n\n---\n\nRequired: No  \nType: String  \nUpdate requires: No interruption"
    }
  }
}